examples/__init__.py
examples/cluster_rules/__init__.py
examples/cluster_rules/allnodes_cpu.py
examples/cluster_rules/bash_version.py
examples/cluster_rules/ntp_compare.py
examples/rules/__init__.py
examples/rules/bash_version.py
examples/rules/hostname_rel.py
examples/rules/sample_script.py
examples/rules/skip_component.py
examples/rules/stand_alone.py
insights/COMMIT
insights/NAME
insights/RELEASE
insights/VERSION
insights/__init__.py
insights/__main__.py
insights/collect.py
insights/command_parser.py
insights/defaults.yaml
insights/settings.py
insights/shell.py
insights/version.py
insights/cleaner/__init__.py
insights/cleaner/filters.py
insights/cleaner/hostname.py
insights/cleaner/ip.py
insights/cleaner/keyword.py
insights/cleaner/mac.py
insights/cleaner/password.py
insights/cleaner/pattern.py
insights/cleaner/utilities.py
insights/client/__init__.py
insights/client/archive.py
insights/client/auto_config.py
insights/client/cert_auth.py
insights/client/client.py
insights/client/collection_rules.py
insights/client/config.py
insights/client/connection.py
insights/client/constants.py
insights/client/core_collector.py
insights/client/crypto.py
insights/client/schedule.py
insights/client/subp.py
insights/client/support.py
insights/client/utilities.py
insights/client/apps/__init__.py
insights/client/apps/ansible/__init__.py
insights/client/apps/ansible/playbook_verifier/__init__.py
insights/client/apps/ansible/playbook_verifier/__main__.py
insights/client/apps/ansible/playbook_verifier/serializer.py
insights/client/apps/ansible/playbook_verifier/contrib/__init__.py
insights/client/apps/ansible/playbook_verifier/contrib/gnupg.py
insights/client/apps/ansible/playbook_verifier/contrib/ruamel_yaml/__init__.py
insights/client/apps/ansible/playbook_verifier/contrib/ruamel_yaml/ruamel/__init__.py
insights/client/apps/ansible/playbook_verifier/contrib/ruamel_yaml/ruamel/yaml/__init__.py
insights/client/apps/ansible/playbook_verifier/contrib/ruamel_yaml/ruamel/yaml/anchor.py
insights_core-3.7.2.dist-info/licenses/LICENSE
insights_core-3.7.2.dist-info/METADATA
insights_core-3.7.2.dist-info/WHEEL
insights_core-3.7.2.dist-info/entry_points.txt
insights_core-3.7.2.dist-info/top_level.txt
insights_core-3.7.2.dist-info/RECORD
